[
    {
        "title": "Marketing Seminar",
        "host": "Marketing Experts",
        "photos": "https://images.unsplash.com/photo-1542744173-8e7e53415bb0?w=500&auto=format&fit=crop&q=60&ixlib=rb-4.1.0&ixid=M3wxMjA3fDB8MHxzZWFyY2h8M3x8ZGlnaXRhbCUyMG1hcmtldGluZyUyMGFnZW5jeXxlbnwwfHwwfHx8MA%3D%3D",
        "typeOfEvent": "Offline",
        "eventDescription": "Stay ahead of the game in the dynamic field of digital marketing by attending the Marketing Seminar organized by Marketing Experts. This offline seminar will be held on August 15th from 10:00 AM to 12:00 PM at Marketing City, situated at 789 Marketing Avenue, City. Join industry leaders Sarah Johnson, Marketing Manager, and Micheal Brown, SEO Specialist, as they delve into the latest trends and strategies in digital marketing. The seminar is open to individuals aged 18 and above and requires a ticket priced at ₹3,000. The dress code for the event is smart casual.",
        "dressCode": "Smart casual",
        "ageRestrictions": "18 and above",
        "eventTags": ["marketing", "digital"],
        "dateAndTime": "Fri Aug 15 2025 at 10:00:00 AM to Fri Aug 15 2025 at 12:00:00 PM",
        "eventVenue": "Marketing City",
        "eventAddress": "789 Marketing Avenue, City",
        "eventPricing": 3000,
        "speakers": ["Sarah Johnson", "Micheal Brown"]
    },
    {
        "title": "Tech Conference",
        "host": "Tech Experts",
        "photos": "https://www.shutterstock.com/image-photo/aerial-view-young-people-coworkers-during-2158299967",
        "typeOfEvent": "Offline",
        "eventDescription": "Stay ahead of the game in the dynamic field of tech networking by attending the Tech Conference organized by Tech Experts. This offline seminar will be held on August 18th from 10:00 AM to 12:00 PM at Silicon Valley Center, situated at 2406 N First Street office building at Silicon Valley Center. Join industry leaders Mukesh Jain, Head of AI Technology, and Ranjan Bhasin, CTO & EVP, as they delve into the latest trends and strategies in tech conference. The seminar is open to individuals aged 18 and above and requires a ticket priced at ₹3,000. The dress code for the event is smart casual.",
        "dressCode": "Smart casual",
        "ageRestrictions":"18 and above",
        "eventTags": ["technology", "networking"],
        "dateAndTime": "Mon Aug 18 2025 at 10:00:00 AM to Mon Aug 18 2025 at 12:00:00 PM",
        "eventVenue": "Silicon Valley Center",
        "eventAddress": "2406 N First Street office building, Silicon Valley Center",
        "eventPricing": 3000,
        "speakers": ["Mukesh Jain", "Ranjan Bhasin"]
    },
    {
        "title": "Design Workshop",
        "host": "Design Experts",
        "photos": "https://images.unsplash.com/photo-1576595580361-90a855b84b20?w=500&auto=format&fit=crop&q=60&ixlib=rb-4.1.0&ixid=M3wxMjA3fDB8MHxzZWFyY2h8M3x8ZGVzaWduJTIwd29ya3Nob3B8ZW58MHx8MHx8fDA%3D",
        "typeOfEvent": "Offline",
        "eventDescription": "Stay ahead of the game in the dynamic field of design practice by attending the Design Workshop organized by Designing Experts. This offline seminar will be held on August 20th from 10:00 AM to 12:00 PM at Designing City, situated at 10/2A, Nepal Bhattacharya St, Anami Sangha, Kalighat, Kolkata. Join industry leaders Dr Andreas Braun, AVL Deutschland GmbH, and  Dr Alexander Gelner, Technical Lead at AVL Deutschland GmbH, as they delve into the latest trends and strategies in design workshop. The seminar is open to individuals aged 18 and above and requires a ticket priced at ₹3,000. The dress code for the event is smart casual.",
        "dressCode": "Smart casual",
        "ageRestrictions": "18 and above",
        "eventTags": ["innovation", "creativity"],
        "dateAndTime": "Thur Aug 21 2025 at 10:00:00 AM to Thur Aug 21 2025 at 12:00:00 PM",
        "eventVenue": "Designing City",
        "eventAddress": "10/2A, Nepal Bhattacharya St, Anami Sangha, Kalighat, Kolkata",
        "eventPricing": 5000,
        "speakers": ["Dr Andreas Braun", "Dr Alexander Gelner"]
    },
    {
        "title": "Photography Workshop",
        "host": "Photography Experts",
        "photos": "https://encrypted-tbn0.gstatic.com/images?q=tbn:ANd9GcRPSt7E1HU17csd_2gj_UGacdWWlQ63jiKWeQ&s",
        "typeOfEvent": "Online",
        "eventDescription": "Stay ahead of the game in the dynamic field of digital photography by attending the Photography Workshop organized by Photography Experts. This online seminar will be held on August 22th from 10:00 AM to 12:00 PM at Galiff Street, situated at Photography Institute Kolkata, West Bengal. Join industry leaders Danielle Feinberg, Pixar Animation Director, and Jimmy Chin, Photographer, as they delve into the latest trends and strategies in photography workshop. The workshop is open to individuals aged 18 and above and requires a ticket priced at ₹2,000. The dress code for the event is smart casual.",
        "dressCode": "Smart casual",
        "ageRestrictions": "18 and above",
        "eventTags": ["portrait", "landscape"],
        "dateAndTime": "Fri Aug 22 2025 at 10:00:00 AM to Fri Aug 22 2025 at 12:00:00 PM",
        "eventVenue": "Galiff Street",
        "eventAddress": "Photography Institute Kolkata, West Bengal",
        "eventPricing": 2000,
        "speakers": ["Danielle Feinberg", "Jimmy Chin"]
    },
    {
        "title": "Data Analytics Seminar",
        "host": "Analytics Experts",
        "photos": "https://www.google.com/imgres?q=Business%20Analytics%20Seminar&imgurl=http%3A%2F%2Fonline.hbs.edu%2FStyle%2520Library%2Fapi%2Fresize.aspx%3Fimgpath%3D%2FPublishingImages%2FBusiness%2520Analytics%2520Meeting.png%26w%3D1200%26h%3D630&imgrefurl=https%3A%2F%2Fonline.hbs.edu%2Fblog%2Fpost%2Fbusiness-analytics-examples&docid=l_oHFKdavlCI5M&tbnid=xQSSk-0QlMsvTM&vet=12ahUKEwjBlNexjpmPAxUKzqACHdwfOfYQM3oFCIcBEAA..i&w=1200&h=630&hcb=2&itg=1&ved=2ahUKEwjBlNexjpmPAxUKzqACHdwfOfYQM3oFCIcBEAA",
        "typeOfEvent": "Offline",
        "eventDescription": "Stay ahead of the game in the dynamic field of analytic practice by attending the Analytics Seminar organized by Analytics Experts. This offline seminar will be held on August 25th from 10:00 AM to 12:00 PM at IIMT Bhubaneswar, situated at Interscience Institute of Managements Technology, Kantabada, Dist. Khorda, Bhubaneswar, Odisha. Join industry leaders Melissa Hollis, Director of Data Analytics at Principal Enterprise Data and Analytics, and Carrie Beam, Director, MSBA Analytics Projects, University of California, as they delve into the latest trends and strategies in analytics workshop. The workshop is open to individuals aged 18 and above and requires a ticket priced at ₹3,000. The dress code for the event is smart casual.",
        "dressCode": "Smart casual",
        "ageRestrictions": "18 and above",
        "eventTags": ["data analytics", "analytics strategy"],
        "dateAndTime": "Mon Aug 25 2025 at 10:00:00 AM to Mon Aug 25 2025 at 12:00:00 PM",
        "eventVenue": "IIMT Bhubaneswar",
        "eventAddress": "Interscience Institute of Managements Technology, Kantabada, Dist. Khorda, Bhubaneswar, Odisha.",
        "eventPricing": 3000,
        "speakers": ["Melissa Hollis", "Carrie Beam"]
    },
    {
        "title": "Business Workshop",
        "host": "Business Experts",
        "photos": "https://www.google.com/imgres?q=business%20workshop%20image&imgurl=https%3A%2F%2Fi0.wp.com%2Fwellbeinginyouroffice.com%2Fwp-content%2Fuploads%2F2024%2F01%2F2024-Blog-pics-Wordpress-5.png%3Ffit%3D1568%252C883%26ssl%3D1&imgrefurl=https%3A%2F%2Fwellbeinginyouroffice.com%2Fcorporate-workshops%2F&docid=YGoGlI2Ra7aB2M&tbnid=hFYlMb-3Z9V4BM&vet=12ahUKEwjlvZf2o5mPAxVS3TgGHacQLTkQM3oECBEQAA..i&w=1567&h=883&hcb=2&ved=2ahUKEwjlvZf2o5mPAxVS3TgGHacQLTkQM3oECBEQAA",
        "typeOfEvent": "Online",
        "eventDescription":"Stay ahead of the game in the dynamic field of business practice by attending the Business Workshop organized by Business Experts. This online seminar will be held on August 27th from 10:00 AM to 12:00 PM at Park Hotel, situated at 17, Park St, Taltala, Kolkata, West Bengal. Join industry leaders Adar Poonawala, CEO of Serum Institute of India and Chairman of Poonawala Fincorp, and Amrita Haldipur, A GirlxTech Champion and Business Writer, as they delve into the latest trends and strategies in business workshop. The workshop is open to individuals aged 18 and above and requires a ticket priced at ₹2,000. The dress code for the event is smart casual.",
        "dressCode": "Smart casual",
        "ageRestrictions": "18 and above",
        "eventTags": ["finance", "leadership"],
        "dateAndTime": "Wed Aug 27 2025 at 10:00:00 AM to Wed Aug 27 2025 at 12:00:00 PM",
        "eventVenue": "Park Hotel",
        "eventAddress": "17, Park St, Taltala, Kolkata, West Bengal",
        "eventPricing": 2000,
        "speakers": ["Adar Poonawala", "Amrita Haldipur"]
    }
]